Metadata-Version: 2.4
Name: py-json-analyzer
Version: 0.4.0
Summary: A powerful CLI and Python library for analyzing, visualizing, exploring, and generating code from JSON data
Author-email: MS-32154 <msttoffg@gmail.com>
Maintainer-email: MS-32154 <msttoffg@gmail.com>
License: MIT
Project-URL: Homepage, https://github.com/MS-32154/py-json-analyzer
Project-URL: Documentation, https://ms-32154.github.io/py-json-analyzer/
Project-URL: Repository, https://github.com/MS-32154/py-json-analyzer
Project-URL: Bug Tracker, https://github.com/MS-32154/py-json-analyzer/issues
Project-URL: Changelog, https://github.com/MS-32154/py-json-analyzer/blob/main/CHANGELOG.md
Keywords: json,analyzer,visualization,json-statistics,plot,jmespath,json-search,cli,interactive-cli,data-analysis,schema,code-generation,go,json-to-go,json-to-golang,python,pydantic,dataclass,json-to-python
Classifier: Development Status :: 4 - Beta
Classifier: Intended Audience :: Developers
Classifier: License :: OSI Approved :: MIT License
Classifier: Operating System :: OS Independent
Classifier: Programming Language :: Python :: 3
Classifier: Programming Language :: Python :: 3.11
Classifier: Programming Language :: Python :: 3.12
Classifier: Programming Language :: Python :: 3.13
Classifier: Topic :: Software Development :: Code Generators
Classifier: Topic :: Software Development :: Libraries :: Python Modules
Classifier: Topic :: Utilities
Classifier: Typing :: Typed
Requires-Python: >=3.11
License-File: LICENSE
Requires-Dist: jmespath>=1.0.1
Requires-Dist: rich>=13.0.0
Requires-Dist: plotly>=5.0.0
Requires-Dist: requests>=2.32.0
Requires-Dist: dateparser>=1.2.0
Requires-Dist: jinja2>=3.0.0
Requires-Dist: prompt-toolkit>=3.0.0
Requires-Dist: windows-curses; sys_platform == "win32"
Provides-Extra: dev
Requires-Dist: pytest>=7.0.0; extra == "dev"
Requires-Dist: pytest-cov>=4.0.0; extra == "dev"
Requires-Dist: black>=23.0.0; extra == "dev"
Requires-Dist: isort>=5.12.0; extra == "dev"
Requires-Dist: mypy>=1.0.0; extra == "dev"
Requires-Dist: flake8>=6.0.0; extra == "dev"
Requires-Dist: types-requests>=2.31.0; extra == "dev"
Requires-Dist: types-dateparser>=1.1.0; extra == "dev"
Provides-Extra: all
Requires-Dist: py-json-analyzer[dev]; extra == "all"
Dynamic: license-file
